<annotation>
	<folder>saiga_images</folder>
	<filename>d39f318s-960.jpg</filename>
	<path>/Users/asyl/Desktop/saiga_images/d39f318s-960.jpg</path>
	<source>
		<database>Unknown</database>
	</source>
	<size>
		<width>900</width>
		<height>600</height>
		<depth>3</depth>
	</size>
	<segmented>0</segmented>
	<object>
		<name>saiga</name>
		<pose>Unspecified</pose>
		<truncated>0</truncated>
		<difficult>0</difficult>
		<bndbox>
			<xmin>364</xmin>
			<ymin>41</ymin>
			<xmax>722</xmax>
			<ymax>544</ymax>
		</bndbox>
	</object>
</annotation>
