<annotation>
	<folder>saiga_images</folder>
	<filename>HAYFe0ieUGaMHG3KnWf3tLcULVV8q97ZzMdigmou.jpg</filename>
	<path>/Users/asyl/Desktop/saiga_images/HAYFe0ieUGaMHG3KnWf3tLcULVV8q97ZzMdigmou.jpg</path>
	<source>
		<database>Unknown</database>
	</source>
	<size>
		<width>2903</width>
		<height>967</height>
		<depth>3</depth>
	</size>
	<segmented>0</segmented>
	<object>
		<name>saiga</name>
		<pose>Unspecified</pose>
		<truncated>0</truncated>
		<difficult>0</difficult>
		<bndbox>
			<xmin>138</xmin>
			<ymin>31</ymin>
			<xmax>1353</xmax>
			<ymax>889</ymax>
		</bndbox>
	</object>
	<object>
		<name>saiga</name>
		<pose>Unspecified</pose>
		<truncated>0</truncated>
		<difficult>0</difficult>
		<bndbox>
			<xmin>1459</xmin>
			<ymin>401</ymin>
			<xmax>2432</xmax>
			<ymax>919</ymax>
		</bndbox>
	</object>
</annotation>
