<annotation>
	<folder>saiga_images</folder>
	<filename>saiga_244.jpg</filename>
	<path>/Users/asyl/Downloads/saiga_images/saiga_244.jpg</path>
	<source>
		<database>Unknown</database>
	</source>
	<size>
		<width>236</width>
		<height>365</height>
		<depth>3</depth>
	</size>
	<segmented>0</segmented>
	<object>
		<name>saiga</name>
		<pose>Unspecified</pose>
		<truncated>1</truncated>
		<difficult>0</difficult>
		<bndbox>
			<xmin>5</xmin>
			<ymin>5</ymin>
			<xmax>232</xmax>
			<ymax>365</ymax>
		</bndbox>
	</object>
</annotation>
