<annotation>
	<folder>saiga_images</folder>
	<filename>Saiga Antelope.png</filename>
	<path>/Users/asyl/Desktop/saiga_images/Saiga Antelope.png</path>
	<source>
		<database>Unknown</database>
	</source>
	<size>
		<width>400</width>
		<height>250</height>
		<depth>3</depth>
	</size>
	<segmented>0</segmented>
	<object>
		<name>saiga</name>
		<pose>Unspecified</pose>
		<truncated>0</truncated>
		<difficult>0</difficult>
		<bndbox>
			<xmin>130</xmin>
			<ymin>2</ymin>
			<xmax>285</xmax>
			<ymax>208</ymax>
		</bndbox>
	</object>
</annotation>
